tests/__init__.py
uniqcharstest7-1.0.dist-info/LICENSE
uniqcharstest7-1.0.dist-info/METADATA
uniqcharstest7-1.0.dist-info/WHEEL
uniqcharstest7-1.0.dist-info/entry_points.txt
uniqcharstest7-1.0.dist-info/top_level.txt
uniqcharstest7-1.0.dist-info/RECORD
